aa/__init__.py
aa/test.py
efg/__init__.py
efg/test2.py
flask_pyinstaller-1.0.0.dist-info/METADATA
flask_pyinstaller-1.0.0.dist-info/WHEEL
flask_pyinstaller-1.0.0.dist-info/top_level.txt
flask_pyinstaller-1.0.0.dist-info/RECORD
